dbtext/__init__.py
dbtext/base_odbc.py
dbtext/db_to_text.py
dbtext/increments.py
dbtext/jsonutils.py
dbtext/mongodb.py
dbtext/mssql_server.py
dbtext/mysql.py
dbtext/postgres.py
dbtext/sqlite3db.py
dbtext/wait.py
dbtext-2.3.1.dist-info/LICENSE
dbtext-2.3.1.dist-info/METADATA
dbtext-2.3.1.dist-info/WHEEL
dbtext-2.3.1.dist-info/top_level.txt
dbtext-2.3.1.dist-info/RECORD
