Metadata-Version: 2.1
Name: dbtext
Version: 2.3.1
Summary: Database to text utility for approval testing
Author: Johan Andersson
Author-email: Geoff Bache <geoff.bache@pobox.com>
License: GNU LESSER GENERAL PUBLIC LICENSE
Project-URL: Homepage, https://github.com/texttest/dbtext
Project-URL: Bug Tracker, https://github.com/texttest/dbtext/issues
Classifier: Programming Language :: Python :: 3
Classifier: License :: OSI Approved :: GNU Lesser General Public License v3 or later (LGPLv3+)
Classifier: Operating System :: OS Independent
Requires-Python: >=3.7
License-File: LICENSE
